setup.py
statsd_mangler/__init__.py
statsd_mangler/__main__.py
statsd_mangler/listener.py
statsd_mangler/mangler.py
statsd_mangler/sender.py
statsd_mangler.egg-info/PKG-INFO
statsd_mangler.egg-info/SOURCES.txt
statsd_mangler.egg-info/dependency_links.txt
statsd_mangler.egg-info/entry_points.txt
statsd_mangler.egg-info/requires.txt
statsd_mangler.egg-info/top_level.txt