Metadata-Version: 1.0
Name: statsd-mangler
Version: 0.1.3
Summary: Namespace mangler for statsd metrics
Home-page: https://github.com/opentable/statsd_mangler
Author: Carl Flippin
Author-email: cflippin@opentable.com
License: MIT
Platform: UNKNOWN
